{
"type": "FeatureCollection",
"name": "selected",
"crs": { "type": "name", "properties": { "name": "urn:ogc:def:crs:OGC:1.3:CRS84" } },
"xy_coordinate_resolution": 1e-06,
"features": [
{ "type": "Feature", "properties": { "id": "cand_1004", "rank": 1, "Score": 73.05, "GapScore": 0.7886, "EquityIndex": 0.3417 }, "geometry": { "type": "Point", "coordinates": [ 4.393771, 51.227161 ] } },
{ "type": "Feature", "properties": { "id": "cand_0984", "rank": 2, "Score": 68.06, "GapScore": 0.9001, "EquityIndex": 0.3548 }, "geometry": { "type": "Point", "coordinates": [ 4.45059, 51.255094 ] } },
{ "type": "Feature", "properties": { "id": "cand_0996", "rank": 3, "Score": 63.88, "GapScore": 0.838, "EquityIndex": 0.431 }, "geometry": { "type": "Point", "coordinates": [ 4.441461, 51.228931 ] } },
{ "type": "Feature", "properties": { "id": "cand_0792", "rank": 4, "Score": 71.33, "GapScore": 1.0, "EquityIndex": 0.2867 }, "geometry": { "type": "Point", "coordinates": [ 4.305989, 51.304195 ] } },
{ "type": "Feature", "properties": { "id": "cand_0368", "rank": 5, "Score": 61.15, "GapScore": 1.0, "EquityIndex": 0.3885 }, "geometry": { "type": "Point", "coordinates": [ 4.340102, 51.17226 ] } },
{ "type": "Feature", "properties": { "id": "cand_1000", "rank": 6, "Score": 71.38, "GapScore": 0.8227, "EquityIndex": 0.3479 }, "geometry": { "type": "Point", "coordinates": [ 4.453951, 51.190878 ] } },
{ "type": "Feature", "properties": { "id": "cand_0841", "rank": 7, "Score": 71.43, "GapScore": 1.0, "EquityIndex": 0.2857 }, "geometry": { "type": "Point", "coordinates": [ 4.306843, 51.311771 ] } },
{ "type": "Feature", "properties": { "id": "cand_0964", "rank": 8, "Score": 72.5, "GapScore": 0.996, "EquityIndex": 0.2761 }, "geometry": { "type": "Point", "coordinates": [ 4.363548, 51.163143 ] } },
{ "type": "Feature", "properties": { "id": "cand_1008", "rank": 9, "Score": 74.14, "GapScore": 0.7662, "EquityIndex": 0.3375 }, "geometry": { "type": "Point", "coordinates": [ 4.464824, 51.232228 ] } },
{ "type": "Feature", "properties": { "id": "cand_0297", "rank": 10, "Score": 72.49, "GapScore": 1.0, "EquityIndex": 0.2751 }, "geometry": { "type": "Point", "coordinates": [ 4.41961, 51.265637 ] } }
]
}
