{"type":"FeatureCollection","name":"selected","crs":{"type":"name","properties":{"name":"urn:ogc:def:crs:OGC:1.3:CRS84"}},"features":[{"type":"Feature","properties":{"id":"cand_0792","rank":1,"Score":71.33,"GapScore":1,"EquityIndex":0.2867},"geometry":{"type":"Point","coordinates":[4.305989,51.304195]}},{"type":"Feature","properties":{"id":"cand_0984","rank":2,"Score":68.06,"GapScore":0.9001,"EquityIndex":0.3548},"geometry":{"type":"Point","coordinates":[4.45059,51.255094]}},{"type":"Feature","properties":{"id":"cand_0841","rank":3,"Score":71.43,"GapScore":1,"EquityIndex":0.2857},"geometry":{"type":"Point","coordinates":[4.306843,51.311771]}},{"type":"Feature","properties":{"id":"cand_0964","rank":4,"Score":72.5,"GapScore":0.996,"EquityIndex":0.2761},"geometry":{"type":"Point","coordinates":[4.363548,51.163143]}},{"type":"Feature","properties":{"id":"cand_0297","rank":5,"Score":72.49,"GapScore":1,"EquityIndex":0.2751},"geometry":{"type":"Point","coordinates":[4.41961,51.265637]}},{"type":"Feature","properties":{"id":"cand_0369","rank":6,"Score":62.22,"GapScore":1,"EquityIndex":0.3778},"geometry":{"type":"Point","coordinates":[4.335438,51.171597]}},{"type":"Feature","properties":{"id":"cand_0885","rank":7,"Score":72.68,"GapScore":1,"EquityIndex":0.2732},"geometry":{"type":"Point","coordinates":[4.317175,51.308273]}},{"type":"Feature","properties":{"id":"cand_0359","rank":8,"Score":67.51,"GapScore":1,"EquityIndex":0.3249},"geometry":{"type":"Point","coordinates":[4.409512,51.244314]}},{"type":"Feature","properties":{"id":"cand_0453","rank":9,"Score":72.88,"GapScore":1,"EquityIndex":0.2712},"geometry":{"type":"Point","coordinates":[4.392436,51.26925]}},{"type":"Feature","properties":{"id":"cand_1000","rank":10,"Score":71.38,"GapScore":0.8227,"EquityIndex":0.3479},"geometry":{"type":"Point","coordinates":[4.453951,51.190878]}}]}