{
"type": "FeatureCollection",
"name": "selected",
"crs": { "type": "name", "properties": { "name": "urn:ogc:def:crs:OGC:1.3:CRS84" } },
"features": [
{ "type": "Feature", "properties": { "id": "cand_0792", "rank": 1, "Score": 71.33, "GapScore": 1.0, "EquityIndex": 0.2867, "demand_weight": 0.1618 }, "geometry": { "type": "Point", "coordinates": [ 4.305989352872397, 51.304195352495128 ] } },
{ "type": "Feature", "properties": { "id": "cand_0984", "rank": 2, "Score": 68.06, "GapScore": 0.9001, "EquityIndex": 0.3548, "demand_weight": 0.183 }, "geometry": { "type": "Point", "coordinates": [ 4.450590111381763, 51.255093510520922 ] } },
{ "type": "Feature", "properties": { "id": "cand_0841", "rank": 3, "Score": 71.43, "GapScore": 1.0, "EquityIndex": 0.2857, "demand_weight": 0.1599 }, "geometry": { "type": "Point", "coordinates": [ 4.306843321955828, 51.311770852000691 ] } },
{ "type": "Feature", "properties": { "id": "cand_0964", "rank": 4, "Score": 72.5, "GapScore": 0.996, "EquityIndex": 0.2761, "demand_weight": 0.1406 }, "geometry": { "type": "Point", "coordinates": [ 4.363547642124012, 51.163143477805576 ] } },
{ "type": "Feature", "properties": { "id": "cand_0297", "rank": 5, "Score": 72.49, "GapScore": 1.0, "EquityIndex": 0.2751, "demand_weight": 0.1386 }, "geometry": { "type": "Point", "coordinates": [ 4.419609762465815, 51.265637292616795 ] } },
{ "type": "Feature", "properties": { "id": "cand_0369", "rank": 6, "Score": 62.22, "GapScore": 1.0, "EquityIndex": 0.3778, "demand_weight": 0.1328 }, "geometry": { "type": "Point", "coordinates": [ 4.335438300625268, 51.171596788584885 ] } },
{ "type": "Feature", "properties": { "id": "cand_0885", "rank": 7, "Score": 72.68, "GapScore": 1.0, "EquityIndex": 0.2732, "demand_weight": 0.1348 }, "geometry": { "type": "Point", "coordinates": [ 4.317175286604534, 51.308272783378769 ] } },
{ "type": "Feature", "properties": { "id": "cand_0359", "rank": 8, "Score": 67.51, "GapScore": 1.0, "EquityIndex": 0.3249, "demand_weight": 0.1251 }, "geometry": { "type": "Point", "coordinates": [ 4.409512453154441, 51.24431430852659 ] } },
{ "type": "Feature", "properties": { "id": "cand_0453", "rank": 9, "Score": 72.88, "GapScore": 1.0, "EquityIndex": 0.2712, "demand_weight": 0.1309 }, "geometry": { "type": "Point", "coordinates": [ 4.392435833921762, 51.269250402152757 ] } },
{ "type": "Feature", "properties": { "id": "cand_1000", "rank": 10, "Score": 71.38, "GapScore": 0.8227, "EquityIndex": 0.3479, "demand_weight": 0.1425 }, "geometry": { "type": "Point", "coordinates": [ 4.453950719419472, 51.190878146723215 ] } }
]
}
